loony_options_lib/black_scholes_info.py
loony_options_lib/loonyfnolibrary.py
loonyfnolibrary-0.0.1.dist-info/LICENSE
loonyfnolibrary-0.0.1.dist-info/METADATA
loonyfnolibrary-0.0.1.dist-info/WHEEL
loonyfnolibrary-0.0.1.dist-info/top_level.txt
loonyfnolibrary-0.0.1.dist-info/RECORD
