Metadata-Version: 2.1
Name: loonyfnolibrary
Version: 0.0.1
Summary: A package to explore options
Author-email: Loonycorn <cloud.user@loonycorn.com>
License: Copyright (c) 2018 The Python Packaging Authority        
Project-URL: Homepage, https://github.com/loonyuser/loonyoptionslib
Project-URL: Bug Tracker, https://github.com/loonyuser/loonyoptionslib/issues
Classifier: Programming Language :: Python :: 3
Classifier: License :: OSI Approved :: MIT License
Classifier: Operating System :: OS Independent
Requires-Python: >=3.7
License-File: LICENSE
